catalystai/__init__.py
catalystai/catalystai.py
catalystai/schema.py
catalystai-1.0.10.dist-info/LICENCE.txt
catalystai-1.0.10.dist-info/METADATA
catalystai-1.0.10.dist-info/WHEEL
catalystai-1.0.10.dist-info/top_level.txt
catalystai-1.0.10.dist-info/RECORD
