Metadata-Version: 2.1
Name: catalystai
Version: 1.0.10
Summary: Catalyst AI SDK
Home-page: 
Author: Catalyst AI
Author-email: contact@catalystai.com
License: Catalyst AI
Keywords: python,first package
Classifier: Development Status :: 2 - Pre-Alpha
Classifier: Intended Audience :: Education
Classifier: Operating System :: MacOS :: MacOS X
Classifier: Operating System :: Microsoft :: Windows
Classifier: Programming Language :: Python :: 3
License-File: LICENCE.txt
Requires-Dist: minio
Requires-Dist: datetime
Requires-Dist: requests
Requires-Dist: urllib3
Requires-Dist: typing
Requires-Dist: pydantic
